vsdkx_connector-2.1-py3.10-nspkg.pth
vsdkx/connector/__init__.py
vsdkx/connector/server.py
vsdkx/connector/client/__init__.py
vsdkx/connector/client/connect_module_pb2.py
vsdkx/connector/client/connect_module_pb2_grpc.py
vsdkx/connector/utils/__init__.py
vsdkx/connector/utils/serialisation.py
vsdkx/connector/utils/yaml_utils.py
vsdkx_connector-2.1.dist-info/LICENSE
vsdkx_connector-2.1.dist-info/METADATA
vsdkx_connector-2.1.dist-info/WHEEL
vsdkx_connector-2.1.dist-info/namespace_packages.txt
vsdkx_connector-2.1.dist-info/top_level.txt
vsdkx_connector-2.1.dist-info/RECORD
