Metadata-Version: 2.1
Name: vsdkx-connector
Version: 2.1
Summary: UNKNOWN
Home-page: https://github.com/natix-io/vsdkx-connector.git
Author: Guja
Author-email: g.mekokishvili@omedia.ge
License: UNKNOWN
Platform: UNKNOWN
License-File: LICENSE
Requires-Dist: grpcio
